COPYRIGHT
LICENSE
MANIFEST.in
NOTICE
README.md
pyproject.toml
setup.cfg
setup.py
flux_burst_compute_engine.egg-info/PKG-INFO
flux_burst_compute_engine.egg-info/SOURCES.txt
flux_burst_compute_engine.egg-info/dependency_links.txt
flux_burst_compute_engine.egg-info/not-zip-safe
flux_burst_compute_engine.egg-info/requires.txt
flux_burst_compute_engine.egg-info/top_level.txt
fluxburst_compute_engine/__init__.py
fluxburst_compute_engine/plugin.py
fluxburst_compute_engine/terraform.py
fluxburst_compute_engine/version.py
fluxburst_compute_engine/templates/__init__.py
fluxburst_compute_engine/templates/burst_boot.sh
fluxburst_compute_engine/templates/default_boot.sh
fluxburst_compute_engine/tf/burst/boot_script.sh
fluxburst_compute_engine/tf/burst/foundation.tf
fluxburst_compute_engine/tf/burst/install_nfs.sh
fluxburst_compute_engine/tf/burst/main.tf
fluxburst_compute_engine/tf/burst/variables.tf